{
  "items": {
    "EthnicWear": {
      "itemsdata": [
        {
          "id": "001",
          "image": "images/ethnic-1.jpg",
          "company": "Mezidi Zineb",
          "item_name": "Women Red & White Traditional Arab Dress",
          "original_price": 3045,
          "current_price": 1770,
          "discount_percentage": 42,
          "return_period": 14,
          "delivery_date": "10 Oct 2023",
          "rating": { "stars": 4.5, "count": 1400 }
        },

        {
          "id": "002",
          "image": "images/ethnic-2.jpg",
          "company": "Mezidi Zineb",
          "item_name": "Women Blue & Golden Traditional Arab Dress",
          "original_price": 5600,
          "current_price": 1770,
          "discount_percentage": 69,
          "return_period": 14,
          "delivery_date": "10 Oct 2023",
          "rating": { "stars": 4.1, "count": 249 }
        },
        {
          "id": "003",
          "image": "images/ethnic-3.jpg",
          "company": "Mezidi Zineb",
          "item_name": "Women White Traditional Arab Dress",
          "original_price": 4200,
          "current_price": 4200,
          "discount_percentage": 0,
          "return_period": 14,
          "delivery_date": "10 Oct 2023",
          "rating": { "stars": 5, "count": 10 }
        },
        {
          "id": "004",
          "image": "images/ethnic-4.jpg",
          "company": "Mezidi Zineb",
          "item_name": "Women Black & Golden Traditional Arab Dress",
          "original_price": 5000,
          "current_price": 1770,
          "discount_percentage": 65,
          "return_period": 14,
          "delivery_date": "10 Oct 2023",
          "rating": { "stars": 4.2, "count": 3500 }
        },
        {
          "id": "005",
          "image": "images/ethnic-5.jpg",
          "company": "Mezidi Zineb",
          "item_name": "Women Green & Golden Traditional Arab Dress",
          "original_price": 14995,
          "current_price": 14995,
          "discount_percentage": 0,
          "return_period": 14,
          "delivery_date": "10 Oct 2023",
          "rating": { "stars": 0, "count": 0 }
        },
        {
          "id": "006",
          "image": "images/ethnic-5.jpg",
          "company": "Mezidi Zineb",
          "item_name": "Women Green & Golden Traditional Arab Dress",
          "original_price": 14995,
          "current_price": 14995,
          "discount_percentage": 0,
          "return_period": 14,
          "delivery_date": "10 Oct 2023",
          "rating": { "stars": 0, "count": 0 }
        },
        {
          "id": "008",
          "image": "images/ethnic-3.jpg",
          "company": "Mezidi Zineb",
          "item_name": "Women White Traditional Arab Dress",
          "original_price": 4200,
          "current_price": 4200,
          "discount_percentage": 0,
          "return_period": 14,
          "delivery_date": "10 Oct 2023",
          "rating": { "stars": 5, "count": 10 }
        },
        {
          "id": "009",
          "image": "images/ethnic-4.jpg",
          "company": "Mezidi Zineb",
          "item_name": "Women Black & Golden Traditional Arab Dress",
          "original_price": 5000,
          "current_price": 1770,
          "discount_percentage": 65,
          "return_period": 14,
          "delivery_date": "10 Oct 2023",
          "rating": { "stars": 4.2, "count": 3500 }
        },
        {
          "id": "010",
          "image": "images/ethnic-1.jpg",
          "company": "Mezidi Zineb",
          "item_name": "Women Red & White Traditional Arab Dress",
          "original_price": 3045,
          "current_price": 1770,
          "discount_percentage": 42,
          "return_period": 14,
          "delivery_date": "10 Oct 2023",
          "rating": { "stars": 4.5, "count": 1400 }
        },
        {
          "id": "007",
          "image": "images/ethnic-2.jpg",
          "company": "Mezidi Zineb",
          "item_name": "Women Blue & Golden Traditional Arab Dress",
          "original_price": 5600,
          "current_price": 1770,
          "discount_percentage": 69,
          "return_period": 14,
          "delivery_date": "10 Oct 2023",
          "rating": { "stars": 4.1, "count": 249 }
        }
      ],"companies":["Mezidi Zineb"]
    },
    "WFH Casual Wear": {
      "itemsdata": [
        {
          "id": "001",
          "image": "images/casual-1.jpg",
          "company": "Ali reza zare",
          "item_name": "Black & White Suit",
          "original_price": 1045,
          "current_price": 606,
          "discount_percentage": 42,
          "return_period": 14,
          "delivery_date": "10 Oct 2023",
          "rating": { "stars": 4.5, "count": 1400 }
        },
        {
          "id": "002",
          "image": "images/casual-2.jpg",
          "company": "Peyman Farmani",
          "item_name": "Blue & White Dress",
          "original_price": 999,
          "current_price": 999,
          "discount_percentage": 0,
          "return_period": 14,
          "delivery_date": "10 Oct 2023",
          "rating": { "stars": 5, "count": 10 }
        },
        {
          "id": "003",
          "image": "images/casual-3.jpg",
          "company": "Podmatch",
          "item_name": "Men Slim Fit Shirt",
          "original_price": 1599,
          "current_price": 639,
          "discount_percentage": 60,
          "rating": { "stars": 4.2, "count": 388 }
        },
        {
          "id": "004",
          "image": "images/casual-4.jpg",
          "company": "M Brauer",
          "item_name": "Men Jacket",
          "original_price": 1599,
          "current_price": 639,
          "discount_percentage": 60,
          "rating": { "stars": 4.2, "count": 388 }
        },
        {
          "id": "005",
          "image": "images/casual-4.jpg",
          "company": "M Brauer",
          "item_name": "Men Jacket",
          "original_price": 1599,
          "current_price": 639,
          "discount_percentage": 60,
          "rating": { "stars": 4.2, "count": 388 }
        },
        {
          "id": "006",
          "image": "images/casual-3.jpg",
          "company": "Podmatch",
          "item_name": "Men Slim Fit Shirt",
          "original_price": 1599,
          "current_price": 639,
          "discount_percentage": 60,
          "rating": { "stars": 4.2, "count": 388 }
        },
        {
          "id": "007",
          "image": "images/casual-2.jpg",
          "company": "Peyman Farmani",
          "item_name": "Blue & White Dress",
          "original_price": 999,
          "current_price": 999,
          "discount_percentage": 0,
          "return_period": 14,
          "delivery_date": "10 Oct 2023",
          "rating": { "stars": 5, "count": 10 }
        },
        {
          "id": "008",
          "image": "images/casual-1.jpg",
          "company": "Ali reza zare",
          "item_name": "Black & White Suit",
          "original_price": 1045,
          "current_price": 606,
          "discount_percentage": 42,
          "return_period": 14,
          "delivery_date": "10 Oct 2023",
          "rating": { "stars": 4.5, "count": 1400 }
        }
      ],"companies":["Ali reza zare","Podmatch","Peyman Farmani","M Brauer"]
    },
    "Mens Activewear": {
      "itemsdata": [
        {
          "id": "001",
          "image": "images/active-1.jpg",
          "company": "Cottonbro",
          "item_name": "Black Track Suit",
          "original_price": 1045,
          "current_price": 606,
          "discount_percentage": 42,
          "return_period": 14,
          "delivery_date": "10 Oct 2023",
          "rating": { "stars": 4.5, "count": 1400 }
        },
        {
          "id": "002",
          "image": "images/active-2.jpg",
          "company": "PNW",
          "item_name": "Brown shirt & Black short pair",
          "original_price": 1399,
          "current_price": 489,
          "discount_percentage": 65,
          "return_period": 14,
          "delivery_date": "10 Oct 2023",
          "rating": { "stars": 4.2, "count": 3500 }
        },
        {
          "id": "003",
          "image": "images/active-3.jpg",
          "company": "Polina",
          "item_name": "White pure cotton T-shirt",
          "original_price": 1399,
          "current_price": 489,
          "discount_percentage": 65,
          "return_period": 14,
          "delivery_date": "10 Oct 2023",
          "rating": { "stars": 4.2, "count": 3500 }
        },
        {
          "id": "004",
          "image": "images/active-4.jpg",
          "company": "Ollivves",
          "item_name": "Tennis Track suit",
          "original_price": 1399,
          "current_price": 489,
          "discount_percentage": 65,
          "return_period": 14,
          "delivery_date": "10 Oct 2023",
          "rating": { "stars": 4.2, "count": 3500 }
        },
        {
          "id": "005",
          "image": "images/active-4.jpg",
          "company": "Ollivves",
          "item_name": "Tennis Track suit",
          "original_price": 1399,
          "current_price": 489,
          "discount_percentage": 65,
          "return_period": 14,
          "delivery_date": "10 Oct 2023",
          "rating": { "stars": 4.2, "count": 3500 }
        },
        {
          "id": "006",
          "image": "images/active-3.jpg",
          "company": "Polina",
          "item_name": "White pure cotton T-shirt",
          "original_price": 1399,
          "current_price": 489,
          "discount_percentage": 65,
          "return_period": 14,
          "delivery_date": "10 Oct 2023",
          "rating": { "stars": 4.2, "count": 3500 }
        },
        {
          "id": "007",
          "image": "images/active-2.jpg",
          "company": "PNW",
          "item_name": "Brown shirt & Black short pair",
          "original_price": 1399,
          "current_price": 489,
          "discount_percentage": 65,
          "return_period": 14,
          "delivery_date": "10 Oct 2023",
          "rating": { "stars": 4.2, "count": 3500 }
        },
        {
          "id": "008",
          "image": "images/active-1.jpg",
          "company": "Cottonbro",
          "item_name": "Black Track Suit",
          "original_price": 1045,
          "current_price": 606,
          "discount_percentage": 42,
          "return_period": 14,
          "delivery_date": "10 Oct 2023",
          "rating": { "stars": 4.5, "count": 1400 }
        }
      ],"companies":["Cottonbro","PNW","Polina","Ollivves"]
    },
    "Western Wear": {
      "itemsdata": [
        {
          "id": "001",
          "image": "images/western-1.jpg",
          "company": "Senya Mitin",
          "item_name": "Cow boy suit",
          "original_price": 1045,
          "current_price": 606,
          "discount_percentage": 42,
          "return_period": 14,
          "delivery_date": "10 Oct 2023",
          "rating": { "stars": 4.5, "count": 1400 }
        },
        {
          "id": "002",
          "image": "images/western-2.jpg",
          "company": "Philippe",
          "item_name": "Men Black & White pent shirt",
          "original_price": 1599,
          "current_price": 495,
          "discount_percentage": 69,
          "return_period": 14,
          "delivery_date": "10 Oct 2023",
          "rating": { "stars": 4.1, "count": 249 }
        },
        {
          "id": "003",
          "image": "images/western-3.jpg",
          "company": "Christian bolt",
          "item_name": "Girls white shirt",
          "original_price": 999,
          "current_price": 999,
          "discount_percentage": 0,
          "return_period": 14,
          "delivery_date": "10 Oct 2023",
          "rating": { "stars": 5, "count": 10 }
        },
        {
          "id": "004",
          "image": "images/western-4.jpg",
          "company": "Abe Camacho",
          "item_name": "Women track suit",
          "original_price": 1399,
          "current_price": 489,
          "discount_percentage": 65,
          "return_period": 14,
          "delivery_date": "10 Oct 2023",
          "rating": { "stars": 4.2, "count": 3500 }
        },
        {
          "id": "005",
          "image": "images/western-4.jpg",
          "company": "Abe Camacho",
          "item_name": "Women track suit",
          "original_price": 1399,
          "current_price": 489,
          "discount_percentage": 65,
          "return_period": 14,
          "delivery_date": "10 Oct 2023",
          "rating": { "stars": 4.2, "count": 3500 }
        },
        {
          "id": "006",
          "image": "images/western-3.jpg",
          "company": "Christian bolt",
          "item_name": "Girls white shirt",
          "original_price": 999,
          "current_price": 999,
          "discount_percentage": 0,
          "return_period": 14,
          "delivery_date": "10 Oct 2023",
          "rating": { "stars": 5, "count": 10 }
        },
        {
          "id": "007",
          "image": "images/western-2.jpg",
          "company": "Philippe",
          "item_name": "Men Black & White pent shirt",
          "original_price": 1599,
          "current_price": 495,
          "discount_percentage": 69,
          "return_period": 14,
          "delivery_date": "10 Oct 2023",
          "rating": { "stars": 4.1, "count": 249 }
        },
        {
          "id": "008",
          "image": "images/western-1.jpg",
          "company": "Senya Mitin",
          "item_name": "Cow boy suit",
          "original_price": 1045,
          "current_price": 606,
          "discount_percentage": 42,
          "return_period": 14,
          "delivery_date": "10 Oct 2023",
          "rating": { "stars": 4.5, "count": 1400 }
        }
      ],"companies":["Senya Mitin","Philippe","Christian bolt","Abe Camacho"]
    },
    "Sportswear": {
      "itemsdata": [
        {
          "id": "001",
          "image": "images/active-4.jpg",
          "company": "Ollivves",
          "item_name": "Tennis Track suit",
          "original_price": 1399,
          "current_price": 489,
          "discount_percentage": 65,
          "return_period": 14,
          "delivery_date": "10 Oct 2023",
          "rating": { "stars": 4.2, "count": 3500 }
        },
        {
          "id": "002",
          "image": "images/Sports-3.jpg",
          "company": "Total Shape",
          "item_name": "Gym Suit",
          "original_price": 1599,
          "current_price": 495,
          "discount_percentage": 69,
          "return_period": 14,
          "delivery_date": "10 Oct 2023",
          "rating": { "stars": 4.1, "count": 249 }
        },
        {
          "id": "003",
          "image": "images/Sports-1.jpg",
          "company": "Sage Friedman",
          "item_name": "Runing Suit",
          "original_price": 999,
          "current_price": 999,
          "discount_percentage": 0,
          "return_period": 14,
          "delivery_date": "10 Oct 2023",
          "rating": { "stars": 5, "count": 10 }
        },
        {
          "id": "004",
          "image": "images/Sports-2.jpg",
          "company": "Sinitta Leunen",
          "item_name": "Men Track Suit",
          "original_price": 1399,
          "current_price": 489,
          "discount_percentage": 65,
          "return_period": 14,
          "delivery_date": "10 Oct 2023",
          "rating": { "stars": 4.2, "count": 3500 }
        },
        {
          "id": "005",
          "image": "images/Sports-2.jpg",
          "company": "Sinitta Leunen",
          "item_name": "Men Track Suit",
          "original_price": 1399,
          "current_price": 489,
          "discount_percentage": 65,
          "return_period": 14,
          "delivery_date": "10 Oct 2023",
          "rating": { "stars": 4.2, "count": 3500 }
        },
        {
          "id": "006",
          "image": "images/Sports-1.jpg",
          "company": "Sage Friedman",
          "item_name": "Runing Suit",
          "original_price": 999,
          "current_price": 999,
          "discount_percentage": 0,
          "return_period": 14,
          "delivery_date": "10 Oct 2023",
          "rating": { "stars": 5, "count": 10 }
        },
        {
          "id": "007",
          "image": "images/Sports-3.jpg",
          "company": "Total Shape",
          "item_name": "Gym Suit",
          "original_price": 1599,
          "current_price": 495,
          "discount_percentage": 69,
          "return_period": 14,
          "delivery_date": "10 Oct 2023",
          "rating": { "stars": 4.1, "count": 249 }
        },
        {
          "id": "008",
          "image": "images/active-4.jpg",
          "company": "Ollivves",
          "item_name": "Tennis Track suit",
          "original_price": 1399,
          "current_price": 489,
          "discount_percentage": 65,
          "return_period": 14,
          "delivery_date": "10 Oct 2023",
          "rating": { "stars": 4.2, "count": 3500 }
        }
      ],"companies":["Sinitta Leunen","Sage Friedman","Total Shape","Ollivves"]
    }
  }
}
